{"video": {"id": "BWVoPxob5DU", "title": "DOM Nodes - Beau teaches JavaScript", "description": "Everything in HTML is a node. Using JavaScript, nodes can be created, modified, or deleted.\n\nThis video covers createElement, appendChild, insertBefore, replaceChild, and removeChild.\n\n\ud83d\udcbb Code: https://codepen.io/beaucarnes/pen/GmrQqa?editors=1010\n\n\ud83d\udd17 More info: https://www.w3schools.com/js/js_htmldom_nodes.asp\n\n\ud83d\udc26 Beau Carnes on Twitter: https://twitter.com/carnesbeau\n\n\u2b50JavaScript Tutorials Playlists\u2b50\n\u25b6JavaScript Basics: https://www.youtube.com/playlist?list=PLWKjhJtqVAbk2qRZtWSzCIN38JC_NdhW5\n\u25b6Data Structures and Algorithms: https://www.youtube.com/playlist?list=PLWKjhJtqVAbkso-IbgiiP48n-O-JQA9PJ\n\u25b6Design Patterns: https://www.youtube.com/playlist?list=PLWKjhJtqVAbnZtkAI3BqcYxKnfWn_C704\n\u25b6ES6: https://www.youtube.com/playlist?list=PLWKjhJtqVAbljtmmeS0c-CEl2LdE-eR_F\n\u25b6Clean Code: https://www.youtube.com/playlist?list=PLWKjhJtqVAbkK24EaPurzMq0-kw5U9pJh\n\n-\nWe're busy people who learn to code, then practice by building projects for nonprofits. Learn Full-stack JavaScript, build a portfolio, and get great references with our open source community.\n\nJoin our community at https://freecodecamp.com\nRead great tech articles at https://medium.freecodecamp.com", "duration": "PT5M5S", "likes": "633", "views": "29298"}, "comments": [{"topLevelComment": {"id": "UgwvgkLqW2vL-54Uubd4AaABAg", "publishedAt": "2021-09-26T07:39:50Z", "author": "Hafizur Rahaman", "text": "Beau is really really good at Cooding    but    can't deliver it properly as a teacher, an example of suppose it's happen but ,why we use this or if I get to different  code then what will do, ... just saying this is happening for that then use this then this then this then thank you and subscribe this channel.   good luck", "likes": 0}}, {"topLevelComment": {"id": "UgzbUGzXsp2MRAaj1yl4AaABAg", "publishedAt": "2021-09-09T21:52:49Z", "author": "Atman Visual", "text": "Clear and straight to the point. Thank you.", "likes": 2}}, {"topLevelComment": {"id": "Ugw-z8-CksNnJghs0Vl4AaABAg", "publishedAt": "2021-02-06T22:07:37Z", "author": "Danielsan B", "text": "1. Learned DOM Node. 2. Learned there are other words to Twinkle Twinkle Little Star I\u2019ve never heard before.", "likes": 2}}, {"topLevelComment": {"id": "Ugz5WJYg13x-QoMk-894AaABAg", "publishedAt": "2020-10-06T22:30:53Z", "author": "gabriel egr", "text": "Thank you. This helped me save thousands of dollars in child support.", "likes": 1}}, {"topLevelComment": {"id": "UgzHUFjbizpD8WeTqJB4AaABAg", "publishedAt": "2020-05-17T17:42:22Z", "author": "Pulok", "text": "pretty much helpful. thanks a lot.", "likes": 0}}, {"topLevelComment": {"id": "UgwpFCr4UlYiov1SX894AaABAg", "publishedAt": "2019-02-23T19:40:32Z", "author": "Alex Declercq", "text": "thanks!", "likes": 0}}, {"topLevelComment": {"id": "UgxHzOut3uVwPE4hWoR4AaABAg", "publishedAt": "2017-08-01T21:50:23Z", "author": "sujith john", "text": "why do i get \" ReferenceError: document is not defined\"  is there something I need to do before running JS ?", "likes": 2}}, {"topLevelComment": {"id": "Ugg7km23_NZ3E3gCoAEC", "publishedAt": "2017-04-28T03:10:55Z", "author": "Benjam\u00edn Camacho", "text": "how i can get a html attribute using js?", "likes": 2}, "replies": [{"id": "Ugg7km23_NZ3E3gCoAEC.8RsyO8jbiAw8RtjkJ5pimw", "publishedAt": "2017-04-28T10:22:15Z", "author": "Ivo", "text": "A quick google search can easily help you out: https://developer.mozilla.org/en-US/docs/Web/API/Element/getAttribute", "likes": 0}]}, {"topLevelComment": {"id": "UgjAyEOszkYUn3gCoAEC", "publishedAt": "2017-04-28T02:14:19Z", "author": "Daniel Padin", "text": "Everything you teach is so succinct. Excellent!", "likes": 3}}, {"topLevelComment": {"id": "UggRu4XvyBLLS3gCoAEC", "publishedAt": "2017-04-28T01:59:54Z", "author": "ViZiO Music", "text": "Amazing!", "likes": 1}}]}