{"video": {"id": "Gj5qBheGOEo", "publishedAt": "2017-02-24T18:04:50Z", "title": "Stacks (Data Structure) - Beau teaches JavaScript", "description": "Stacks are a programming data structure. Learn how they work in JavaScript.\n\nCode: \n\ud83d\udd17 http://codepen.io/beaucarnes/pen/yMBGbR?editors=0012\nMore information:\n\ud83d\udd17 http://radar.oreilly.com/2014/03/stacks-in-javascript.html\n\n\ud83d\udc26Beau Carnes on Twitter: https://twitter.com/carnesbeau\n\n\ud83d\udd17 Check out Beau's algorithms course from Manning Publications: https://www.manning.com/livevideo/algorithms-in-motion?a_aid=algmotion&a_bid=9022d293\n\n\u2b50JavaScript Playlists\u2b50\n\u25b6Design Patterns: https://www.youtube.com/playlist?list=PLWKjhJtqVAbnZtkAI3BqcYxKnfWn_C704\n\u25b6JavaScript Basics: https://www.youtube.com/playlist?list=PLWKjhJtqVAbk2qRZtWSzCIN38JC_NdhW5\n\u25b6ES6: https://www.youtube.com/playlist?list=PLWKjhJtqVAbljtmmeS0c-CEl2LdE-eR_F\n\u25b6Data Structures and Algorithms: https://www.youtube.com/playlist?list=PLWKjhJtqVAbkso-IbgiiP48n-O-JQA9PJ\n\u25b6Clean Code: https://www.youtube.com/playlist?list=PLWKjhJtqVAbkK24EaPurzMq0-kw5U9pJh\n\n-\nWe're busy people who learn to code, then practice by building projects for nonprofits. Learn Full-stack JavaScript, build a portfolio, and get great references with our open source community.\n\nJoin our community at https://freecodecamp.com\nFollow us on twitter: https://twitter.com/freecodecamp\nLike us on Facebook: https://www.facebook.com/freecodecamp\nFollow Quincy on Quora: https://www.quora.com/Quincy-Larson", "duration": "PT8M47S", "likes": "977", "views": "89984"}, "comments": [{"topLevelComment": {"id": "UgyefuULu-Vl8wvO5dF4AaABAg", "publishedAt": "2022-01-04T09:54:38Z", "author": "Andrii", "text": "Really !? mb FILO ?! First In Last Out.", "likes": 0}}, {"topLevelComment": {"id": "UgzqvDdw8VdihNOVWHN4AaABAg", "publishedAt": "2021-04-19T11:18:43Z", "author": "Sam", "text": "AWESOME!!!", "likes": 0}}, {"topLevelComment": {"id": "UgyUUclJJM6J_ypF79Z4AaABAg", "publishedAt": "2021-03-10T00:06:01Z", "author": "kashinath arora", "text": "One Question; what if we peek on empty stack here ? Shouldn't we check in peek function whether count is 0 or not ?\nIs it something like it should return -1 in case of empty stack ? But here storage object don't have -1 as a key... suggestions would be appreciated.", "likes": 1}}, {"topLevelComment": {"id": "UgzcnJtzw73qecW-LZ54AaABAg", "publishedAt": "2020-05-29T13:55:13Z", "author": "Abdallah Rawashdeh", "text": "Why he used storage as object [not array] in the Stack implementation ?", "likes": 0}, "replies": [{"id": "UgzcnJtzw73qecW-LZ54AaABAg.99F3-FMo5KP9CHj4QjHI9d", "publishedAt": "2020-08-13T04:24:20Z", "author": "Utkarsh Singh", "text": "Because you can just pop and push on an array in JS so there would be no learning of how to actually implement it", "likes": 1}]}, {"topLevelComment": {"id": "Ugwz3c0NBz9_6Hs6wKN4AaABAg", "publishedAt": "2020-03-22T23:18:14Z", "author": "Hasan Said", "text": "Kinda of a stupid question but how was he able to make a new Stack() obj from a function?", "likes": 0}, "replies": [{"id": "Ugwz3c0NBz9_6Hs6wKN4AaABAg.96WyNOrNDY-96b3RIZZ6Cy", "publishedAt": "2020-03-24T22:47:24Z", "author": "Marouane Souda", "text": "Stack() is a constructor function. It \"constructs\" objects or \"instances\" by using the keyword \"new\" before calling it, and then storing the newly created object inside of a variable. The \"new\" keyword takes care of all of that behind the scenes.", "likes": 1}]}, {"topLevelComment": {"id": "UgxQLqCRXCntQMJxSs94AaABAg", "publishedAt": "2020-01-08T06:24:34Z", "author": "Sophia Lee", "text": "First In Last Out :)", "likes": 3}, "replies": [{"id": "UgxQLqCRXCntQMJxSs94AaABAg.93WbYLJsaJm9539w02tWZJ", "publishedAt": "2020-02-15T12:59:20Z", "author": "ouf cena", "text": "1st one to stuck inside", "likes": 0}]}, {"topLevelComment": {"id": "UgymL0Q1KyBi0TxMVa94AaABAg", "publishedAt": "2019-09-17T21:11:37Z", "author": "PlatinumBuckGorilla", "text": "this.storage.length", "likes": 0}}, {"topLevelComment": {"id": "UgwiaFCBmHmAceWbtph4AaABAg", "publishedAt": "2019-09-08T17:13:27Z", "author": "It's Aaron", "text": "\ud83d\udca4Enjoyed every last bit of it", "likes": 0}}, {"topLevelComment": {"id": "UgxQkEtdug_YyH-zfHB4AaABAg", "publishedAt": "2019-06-20T10:52:29Z", "author": "Michael Owolabi", "text": "A good and concise explanation of stack. Thanks Beau", "likes": 0}}, {"topLevelComment": {"id": "UgzDLJ8fC2kzHWa8qRx4AaABAg", "publishedAt": "2019-04-11T10:45:26Z", "author": "jahanzaib shahid", "text": "which tool is this ??", "likes": 0}}, {"topLevelComment": {"id": "Ugwz_dfE4B1STTzgCx14AaABAg", "publishedAt": "2018-08-01T03:20:33Z", "author": "Alexis Z", "text": "Very clear example of stack. THANK YOU!", "likes": 0}, "replies": [{"id": "Ugwz_dfE4B1STTzgCx14AaABAg.8jOS98_-7tK8l4tSGGyd1K", "publishedAt": "2018-09-12T06:05:48Z", "author": "E Hayrapetyan", "text": "plz can u say , i dont understand why he creates second for loop with method pop(), it removing method yeah?", "likes": 0}]}, {"topLevelComment": {"id": "Ugy-sF906Q1fcc4UC8B4AaABAg", "publishedAt": "2018-04-12T15:19:12Z", "author": "Ali Kalkandelen", "text": "Where are you from man i love the way you say \"Stack\" you hold your a's so it sounds more like Staack which is cool.", "likes": 4}, "replies": [{"id": "Ugy-sF906Q1fcc4UC8B4AaABAg.8ewv9dnOK459MskgcmSG2S", "publishedAt": "2021-05-03T12:03:30Z", "author": "Ilir Bajrami", "text": "@Ali Kalkandelen im sure they had a last name here, but there was an agreement between serbians and turks at that time to ethnic cleanse the area from albanians which led to hundred of thousands albanians migrate to turkey where they got completely asimilated. today there are about 5million albanian descendant population (more than Albania as a country itself) living in turkey without any right to remember their language, culture etc... just as your grandfather. even though this is completely different subject from the video above, this is an interesting discovery to meet someone online such as your case :) hope to meet you in Tetov\u00eb someday!", "likes": 0}, {"id": "Ugy-sF906Q1fcc4UC8B4AaABAg.8ewv9dnOK459MrUv1aqgCO", "publishedAt": "2021-05-03T00:17:41Z", "author": "Ali Kalkandelen", "text": "@Ilir Bajrami I'm from Turkey, but my grandfather came from Kalkandelen Macedonia that's how I have the last name. Back then there were no last names and everyone was assigned a last name to where they lived.", "likes": 0}, {"id": "Ugy-sF906Q1fcc4UC8B4AaABAg.8ewv9dnOK459Mq73_1_lu3", "publishedAt": "2021-05-02T11:30:01Z", "author": "Ilir Bajrami", "text": "you know which city is 'Kalkandelen'? in albanian its Tetov\u00eb and according to your second name your origin must be from the city where i come from :) and im sure ur albanian :)", "likes": 0}]}, {"topLevelComment": {"id": "UgwCpfPVOdg9bFE0lLh4AaABAg", "publishedAt": "2018-03-22T13:19:09Z", "author": "Eldar Iamel", "text": "function isPalindrome(str) {\n  for (let i=0; i < str.length - i; i++) {\n    if(str[i]!==str[str.length-1-i]) return false\n  }\n  return true\n}\nYou can access string with [i]ndexes. \nYou don't need to use additional variables (except iterator). \nYou don't need to modify the original string or split it into an array and modify it (with pop and especially shift). \nYou may add a length>0 check if you feel like an empty string is not a palindrome.\n\nComments are welcome.\n\nUPD. I forgot to mention that it will work with arrays too.", "likes": 1}}, {"topLevelComment": {"id": "UgyCQ8LOb3cRQzYpjvl4AaABAg", "publishedAt": "2018-01-04T15:41:13Z", "author": "Thomas Faller", "text": "Great video as usual! I love the \"80s\" sound of your keyboard aha :P", "likes": 5}}, {"topLevelComment": {"id": "UgwbHY0UiCqh0XpJ5_x4AaABAg", "publishedAt": "2017-09-19T10:04:03Z", "author": "Byazit Bostami", "text": "Why did you use this.count=0 instead of var count=0 ?", "likes": 0}, "replies": [{"id": "UgwbHY0UiCqh0XpJ5_x4AaABAg.8XgV7wW1Qq38YLzooYRHZ5", "publishedAt": "2017-10-05T22:09:01Z", "author": "Houman", "text": "The reason is that var defines a global variables, and so if you have two different stack functions, each will try to change the same global variable!\n\nGenerally speaking though, it is strongly preferred to use 'let' and 'const' to define variables, instead of var. You really shouldn't need to use 'var' ever", "likes": 2}]}, {"topLevelComment": {"id": "Ugiss4U2PjJzL3gCoAEC", "publishedAt": "2017-07-22T22:02:42Z", "author": "KAWAII OBAMA", "text": "Beau is the best Senpai ever! He explains everything so clearly.", "likes": 3}}, {"topLevelComment": {"id": "UghSua_D7UBD0XgCoAEC", "publishedAt": "2017-07-16T08:16:24Z", "author": "Rahul Raj", "text": "For simple explanation of concept in data mining visit my blog\nhttps://dataminingsimpleexplanations.blogspot.in/", "likes": 0}}, {"topLevelComment": {"id": "Ugi4UsXutUpNx3gCoAEC", "publishedAt": "2017-07-02T06:01:30Z", "author": "blehbleh", "text": "Great video!  One question, \n\nEven though pop() removes the top element from the stack, the storage array still preservers the same size (for example, say we've pushed onto storage [10,20,40], then popped the stack, we get [10,20,], yet when doing console.log(stack.storage.length), we still get 3, not 2.", "likes": 1}, "replies": [{"id": "Ugi4UsXutUpNx3gCoAEC.8UVd_PhowIG9VQKSFt6cCN", "publishedAt": "2021-12-01T18:30:02Z", "author": "wanderlust_rj51", "text": "I know it's too late to reply but for the people who are watching this video now and getting the same error, \nreplace line \"delete this.storage[this.count]\" \nwith \"this.storage.splice[this.storage.length-1, 1)\" or \"this.storage.splice[this.count, 1)\"", "likes": 1}]}, {"topLevelComment": {"id": "UgiIf2SIwfNpmXgCoAEC", "publishedAt": "2017-06-06T15:29:06Z", "author": "atsepa", "text": "awesome man!!! Thanks! !!", "likes": 0}}, {"topLevelComment": {"id": "Ughl0qODsSBDD3gCoAEC", "publishedAt": "2017-04-28T21:22:27Z", "author": "Joel Rivera", "text": "CounterStrike !!!  <3", "likes": 1}}, {"topLevelComment": {"id": "UghxKI6QdoeQNHgCoAEC", "publishedAt": "2017-02-26T11:54:21Z", "author": "Siderite Zackwehdex", "text": "Beau, I love your videos, but please be more careful. There are a bunch of mistakes in almost every video you make. You can easily edit them or even redo them. A stack is not a First In First Out, that's a queue. I don't mind small mistakes, but if they are perennial they become annoying.", "likes": 38}, "replies": [{"id": "UghxKI6QdoeQNHgCoAEC.8PRpnY5ln8V90d1F-wvDoZ", "publishedAt": "2019-10-28T13:58:21Z", "author": "OneManShow", "text": "@Carnaru Valentin : Thank you sir!", "likes": 1}, {"id": "UghxKI6QdoeQNHgCoAEC.8PRpnY5ln8V90czyHRVWaM", "publishedAt": "2019-10-28T13:38:28Z", "author": "Carnaru Valentin", "text": "@OneManShow When is the case, I will let you know!", "likes": 0}, {"id": "UghxKI6QdoeQNHgCoAEC.8PRpnY5ln8V90cwJfGuWe7", "publishedAt": "2019-10-28T13:06:34Z", "author": "OneManShow", "text": "Carnaru Valentin : I have! I hope you learned something!", "likes": 2}, {"id": "UghxKI6QdoeQNHgCoAEC.8PRpnY5ln8V90cHm318zlA", "publishedAt": "2019-10-28T07:03:34Z", "author": "Carnaru Valentin", "text": "@OneManShow Next time use your energy for something more constructive!", "likes": 0}, {"id": "UghxKI6QdoeQNHgCoAEC.8PRpnY5ln8V90bnrzPWZkX", "publishedAt": "2019-10-28T02:33:30Z", "author": "OneManShow", "text": "@Carnaru Valentin Are you serious right now? Anyone who upvoted your comment should NOT be a programmer. We don't need any more \"Programmers\" who hack things together and hope it works. We need programmers who are thorough, and thoughtful, and make sure their code is tested correctly before deployment. If you think that it isn't worth the teacher's time to correct mistakes in their \"free\" course, then you're probably the type to make programming errors and not care less about the consequences. By the way: the course isn't free, we all spend hours of our lives watching these tutorial videos. Maybe you value your time as worthless. I do not.", "likes": 1}]}, {"topLevelComment": {"id": "UggYKCEI6KP7IHgCoAEC", "publishedAt": "2017-02-26T04:13:08Z", "author": "Pan Zheng", "text": "Awesome lessons!!! And please do more data structure videos", "likes": 5}}, {"topLevelComment": {"id": "UghKs5_Yx9-57ngCoAEC", "publishedAt": "2017-02-25T10:29:22Z", "author": "Jonathan Lee", "text": "function isPalindrone(str) {\n  var stack = str.split('')\n  var isPalindrone = true\n  while(isPalindrone === true && stack.length > 1) {\n    isPalindrone = stack.shift() === stack.pop()\n  }\n  return isPalindrone\n}", "likes": 1}, "replies": [{"id": "UghKs5_Yx9-57ngCoAEC.8PP6HBMTR_Q953B1Ur-73U", "publishedAt": "2020-02-15T13:08:58Z", "author": "ouf cena", "text": "@Santhosh Sundar GJ", "likes": 0}, {"id": "UghKs5_Yx9-57ngCoAEC.8PP6HBMTR_Q8bHjb1b7XRV", "publishedAt": "2018-01-11T16:35:56Z", "author": "Santhosh Sundar", "text": "const checkPalindrome = (str) => str.split('').reverse().join('') === str;", "likes": 2}, {"id": "UghKs5_Yx9-57ngCoAEC.8PP6HBMTR_Q8X5uSXkjUGh", "publishedAt": "2017-09-04T19:42:54Z", "author": "jaime salvador martinez simental", "text": "function isPalindrone(str) {\n return str.split('').reverse().join('') === str;\n}", "likes": 2}, {"id": "UghKs5_Yx9-57ngCoAEC.8PP6HBMTR_Q8SAiHh_rkrX", "publishedAt": "2017-05-05T09:55:48Z", "author": "Matt F.", "text": "wat.", "likes": 1}]}, {"topLevelComment": {"id": "UgjQuiLKtg9IQXgCoAEC", "publishedAt": "2017-02-25T05:07:50Z", "author": "Michael Borado", "text": "It should be First In Last Out or Last In First Out instead of First In First Out which is a queue", "likes": 1}, "replies": [{"id": "UgjQuiLKtg9IQXgCoAEC.8POXUCWxHQG8PPF-s0tNJd", "publishedAt": "2017-02-25T11:45:39Z", "author": "Beau Carnes", "text": "Thanks for catching that! I just added a note on the video.", "likes": 2}]}, {"topLevelComment": {"id": "UggDafxLtQa09ngCoAEC", "publishedAt": "2017-02-24T20:33:40Z", "author": "trapped cat", "text": "these js videos are so good!", "likes": 3}}, {"topLevelComment": {"id": "UgiMkgBemUsirXgCoAEC", "publishedAt": "2017-02-24T19:06:27Z", "author": "mrprofessor", "text": "some really good lessons", "likes": 5}}]}