{"video": {"id": "HvxmF0FUwrM", "title": "SQL Server Performance Essentials \u2013 Full Course", "description": "In this course, Essentials of SQL Server Performance For Every Developer, you will see how to diagnose what is happening with a slow running SQL statement and what strategies are available to make these statements run faster. \n\nBy the end of this course, you as an application developer will have the tools you need to troubleshoot performance problems you may encounter when using SQL Server.\n\n\ud83d\udcbb Code, links, Dynamic Views(DMVs), and Database Backups: https://github.com/iCodeMechanic/Essentials-of-Sql-Server-Performance-for-Every-Developer\n\n\u270f\ufe0f Course from Rajan Arora. Check out his channel: https://www.youtube.com/c/ICodeMechanic\n\n\u2b50\ufe0f Course Contents \u2b50\ufe0f\n\u2328\ufe0f (0:00:00) Introduction\n\nGetting Started\n\u2328\ufe0f (0:00:53) 1.1 Course Introduction\n\u2328\ufe0f (0:04:07) 1.2 Why Developers should Understand SQL Performance\n\u2328\ufe0f (0:06:20) 1.3 Tools you Need\n\u2328\ufe0f (0:09:30) 1.4 Restore the Sample Database\n\u2328\ufe0f (0:12:04) 1.5 Table Concept\n\u2328\ufe0f (0:17:12) 1.6 Index Concept\n\u2328\ufe0f (0:20:32) 1.7 Summary\n\nAnalyzing SQL Statements for Performance\n\u2328\ufe0f (0:22:12) 2.1 Introduction\n\u2328\ufe0f (0:24:55) 2.2 Understanding How SQL Server Will Execute a SQL Statement\n\u2328\ufe0f (0:29:33) 2.3 Reading and Interpreting an Execution Plan for a SQL Statement\n\u2328\ufe0f (0:39:44) 2.4 Getting Execution Statistics for a SQL Statement\n\u2328\ufe0f (0:45:29) 2.5 Improving Statement Performance by Adding an Index\n\u2328\ufe0f (0:52:11) 2.6 Rewriting SQL Statements for Improved Performance\n\u2328\ufe0f (0:58:32) 2.7 Common Execution Plan Operations\n\u2328\ufe0f (1:03:50) 2.8 Summary\n\nBuilding Indexes\n\u2328\ufe0f (1:07:30) 3.1 Introduction\n\u2328\ufe0f (1:09:09) 3.2 Index Terminology Refresher\n\u2328\ufe0f (1:12:11) 3.3 What Should I Index in My Database?\n\u2328\ufe0f (1:16:16) 3.4 Why Index Column Order Matters\n\u2328\ufe0f (1:23:39) 3.5 Index Selectivity Explained\n\u2328\ufe0f (1:36:23) 3.6 LIKE Clauses and Index Selectivity\n\u2328\ufe0f (1:40:27) 3.7 How Functions in the WHERE Clause Affect Indexes\n\u2328\ufe0f (1:46:10) 3.8 Include Columns and Covering Indexes\n\u2328\ufe0f (1:50:40) 3.9 Over-indexing\n\u2328\ufe0f (1:54:40) 3.10 Interpreting SQL Server Index Recommendations\n\u2328\ufe0f (1:57:38) 3.11 Summary\n\nFinding Bottlenecks in SQL Server Performance\n\u2328\ufe0f (2:03:19) 4.1 Introduction\n\u2328\ufe0f (2:08:36) 4.2 Getting Information About SQL Server Sessions and Resource Usage\n\u2328\ufe0f (2:12:02) 4.3 Finding What SQL Statements are Currently Executing\n\u2328\ufe0f (2:18:47) 4.4 Finding the Slowest, Most Expensive SQL Statements\n\u2328\ufe0f (2:24:13) 4.5 Getting SQL Server's Recommendations on Missing Indexes\n\u2328\ufe0f (2:29:38) 4.6 Finding Indexes That are Not Being Used\n\u2328\ufe0f (2:34:13) 4.7 Summary\n\nCapturing Trace Logs of Application from SQL Server\n\u2328\ufe0f (2:35:55) 5.1 Introduction\n\u2328\ufe0f (2:42:03) 5.2 Setting up a SQL Profiler Trace\n\u2328\ufe0f (2:49:59) 5.3 Running a SQL Profiler Trace\n\u2328\ufe0f (2:55:22) 5.4 Running a Trace as a Server Side Trace\n\u2328\ufe0f (3:03:19) 5.5 Introduction to Using Extended Events for SQL Tracing\n\u2328\ufe0f (3:06:58) 5.6 Setting up an Extended Events Trace Session\n\u2328\ufe0f (3:16:50) 5.7 Running and Configuring the Display Settings for an Extended Events Trace\n\u2328\ufe0f (3:20:38) 5.8 Analyzing Extended Events Trace Data\n\u2328\ufe0f (3:27:10) 5.9 Using Extended Events in SQL Azure\n\u2328\ufe0f (3:31:36) 5.10 Summary\n\nApply Common Practices for Better Performance\n\u2328\ufe0f (3:35:47) 6.1 Introduction\n\u2328\ufe0f (3:37:17) 6.2 Use Parameterized SQL\n\u2328\ufe0f (3:42:59) 6.3 Are Stored Procedures Faster Than SQL in Application Code?\n\u2328\ufe0f (3:43:04) 6.4 Commit Behavior and Performance\n\u2328\ufe0f (3:50:16) 6.5 Object Relational Mappers Just Generate SQL\n\u2328\ufe0f (3:53:19) 6.6 Solving the N+1 Selects Problem\n\u2328\ufe0f (3:59:56) 6.7 Summary\n\n\ud83c\udf89 Thanks to our Champion and Sponsor supporters:\n\ud83d\udc7e Raymond Odero\n\ud83d\udc7e Agust\u00edn Kussrow\n\ud83d\udc7e aldo ferretti\n\ud83d\udc7e Otis Morgan\n\ud83d\udc7e DeezMaster\n\n--\n\nLearn to code for free and get a developer job: https://www.freecodecamp.org\n\nRead hundreds of articles on programming: https://freecodecamp.org/news", "duration": "PT4H3M27S", "likes": "3519", "views": "116657"}, "comments": [{"topLevelComment": {"id": "Ugw9ilv69-slyZM4ZA54AaABAg", "publishedAt": "2022-05-19T10:25:55Z", "author": "Code Mechanic", "text": "Hey! this is Rajan Arora. Thank you so much Beau for posting my tutorial. I hope this will help all the viewers to tune their SQL Statements in MS SQL Server. I hope we have more collaboration like this in the future!", "likes": 50}, "replies": [{"id": "Ugw9ilv69-slyZM4ZA54AaABAg.9bCcOKc8pIK9gcotqYl4Kd", "publishedAt": "2022-10-01T06:31:41Z", "author": "Code Mechanic", "text": "@Sheen Varghese Thank you so much!!", "likes": 0}, {"id": "Ugw9ilv69-slyZM4ZA54AaABAg.9bCcOKc8pIK9gUDc1FdK4N", "publishedAt": "2022-09-27T13:04:02Z", "author": "Sheen Varghese", "text": "@Code Mechanic Great content Raj! Subscribed to your channel!", "likes": 0}, {"id": "Ugw9ilv69-slyZM4ZA54AaABAg.9bCcOKc8pIK9bWcD06DLUK", "publishedAt": "2022-05-27T04:49:11Z", "author": "Code Mechanic", "text": "@Divakar Raj Link is mention in the description", "likes": 0}, {"id": "Ugw9ilv69-slyZM4ZA54AaABAg.9bCcOKc8pIK9bWbMjePvIW", "publishedAt": "2022-05-27T04:41:47Z", "author": "Code Mechanic", "text": "@Ahmad Murey Thanks for the feedback", "likes": 1}, {"id": "Ugw9ilv69-slyZM4ZA54AaABAg.9bCcOKc8pIK9bWbBMWtTir", "publishedAt": "2022-05-27T04:40:13Z", "author": "Code Mechanic", "text": "@Maaz Qureshi Thanks for the feedback", "likes": 0}]}, {"topLevelComment": {"id": "Ugw5NzAsq-7-Ia3sQE54AaABAg", "publishedAt": "2022-11-14T08:03:01Z", "author": "Alec D", "text": "thanks for this great video. at 1:46 , can we run the SELECT * FROM Applicants WHERE EMailLocalPart = 'LouiseSmith' because you have created an index on EmailLocalPart? Why do you still run the original statement with functions used in WHERE clause? Please advise, thanks", "likes": 0}}, {"topLevelComment": {"id": "Ugzw8hmJblLTSAG90VB4AaABAg", "publishedAt": "2022-10-31T11:21:15Z", "author": "Hassan Raza", "text": "Kindly create a full course on SQL Server - DBA", "likes": 1}}, {"topLevelComment": {"id": "UgwosVcAKCWDCOg9uvR4AaABAg", "publishedAt": "2022-09-12T04:24:02Z", "author": "H1\u20b9 per Month", "text": "I have a query, it works very speed but suddenly it's taking more time, I can optimize but I want to know the root cause why it works before why it's not now ?, can you please tell me what can I do to know the root cause", "likes": 0}}, {"topLevelComment": {"id": "Ugwm5lmHK3k2ASXSneR4AaABAg", "publishedAt": "2022-06-20T17:16:12Z", "author": "TingXi Lin", "text": "Thank you for sharing this good course.Can you share the ppt.", "likes": 0}}, {"topLevelComment": {"id": "UgycJzh3u3H56ItOsE54AaABAg", "publishedAt": "2022-06-08T20:20:52Z", "author": "slah Omar", "text": "What's a great video, are concepts and strategies in this course applicable for PostgresDB ?? or for all SQL languages no matter whether it's SQL server or PostgressDB ????", "likes": 0}, "replies": [{"id": "UgycJzh3u3H56ItOsE54AaABAg.9c1BNIvtw9L9kNsTpkM-gI", "publishedAt": "2023-01-02T12:00:40Z", "author": "Phenomenon", "text": "Did you find an answer for your question ?", "likes": 0}]}, {"topLevelComment": {"id": "UgwDNCUXDvlLa-noPVV4AaABAg", "publishedAt": "2022-06-03T10:09:10Z", "author": "Anand Vardhan", "text": "This is wonderful course. I have been waiting to learn these techniques. Thank you so much for making it.", "likes": 0}, "replies": [{"id": "UgwDNCUXDvlLa-noPVV4AaABAg.9boDOjgQoat9ckFXABu9SJ", "publishedAt": "2022-06-26T17:42:13Z", "author": "Code Mechanic", "text": "Thanks for the feedback", "likes": 0}]}, {"topLevelComment": {"id": "UgxoZfi18QZcs_aanKd4AaABAg", "publishedAt": "2022-06-01T11:17:58Z", "author": "Yasu Mori", "text": "I executed the same query as the section 2.6 at (0:52:30) and got a different result that was an empty table. I wonder why ce.CourseOfferingId is specified as NULL. It supposes to have a not-null constraints. Would you please teach me?", "likes": 3}}, {"topLevelComment": {"id": "UgypzDInpNhMHyS84p94AaABAg", "publishedAt": "2022-05-31T10:15:06Z", "author": "Ashen Upendra Disanayaka", "text": "Very useful, Thank you !!!", "likes": 1}, "replies": [{"id": "UgypzDInpNhMHyS84p94AaABAg.9bgVgbA1arr9bixiRPtrG7", "publishedAt": "2022-06-01T09:07:14Z", "author": "Code Mechanic", "text": "Thanks for the feedback", "likes": 0}]}, {"topLevelComment": {"id": "UgwURhKdi68-pwwL4iF4AaABAg", "publishedAt": "2022-05-30T16:37:37Z", "author": "Clean Zerg", "text": "if youtube allows users to change the accent of the videos based on the scripts, that would be great", "likes": 0}}, {"topLevelComment": {"id": "UgwxRMU3CRAzJ380R7d4AaABAg", "publishedAt": "2022-05-29T05:29:58Z", "author": "Sa Play", "text": "Great", "likes": 1}, "replies": [{"id": "UgwxRMU3CRAzJ380R7d4AaABAg.9baqTToO8Ek9bde0AU1e5-", "publishedAt": "2022-05-30T07:38:50Z", "author": "Code Mechanic", "text": "Thanks for the feedback", "likes": 0}]}, {"topLevelComment": {"id": "Ugwo8ZqC2HGNxbyWaRh4AaABAg", "publishedAt": "2022-05-28T19:16:18Z", "author": "Adwait Chavan", "text": "Can you please build a program for Postgres Performance essentials", "likes": 2}, "replies": [{"id": "Ugwo8ZqC2HGNxbyWaRh4AaABAg.9b_kEnAfxxW9bduupnb0D6", "publishedAt": "2022-05-30T10:06:31Z", "author": "Adwait Chavan", "text": "@Code Mechanic Thank you", "likes": 1}, {"id": "Ugwo8ZqC2HGNxbyWaRh4AaABAg.9b_kEnAfxxW9bdeaWdmnhU", "publishedAt": "2022-05-30T07:43:56Z", "author": "Code Mechanic", "text": "Try my best to look into this.", "likes": 1}]}, {"topLevelComment": {"id": "UgyeOpyUBvVXqK-LALZ4AaABAg", "publishedAt": "2022-05-27T17:07:34Z", "author": "Norman Fleming", "text": "As someone that has been writing code for 40 years I totally agree with your initial premise. If you are writing the SQL you need to understand how it operates and the costs/tradeoffs you may be making. Your video content was very well organized and presented.", "likes": 7}, "replies": [{"id": "UgyeOpyUBvVXqK-LALZ4AaABAg.9bXwi4NyMiL9bixzZwYJmp", "publishedAt": "2022-06-01T09:09:35Z", "author": "Code Mechanic", "text": "Thank you for the feedback", "likes": 0}]}, {"topLevelComment": {"id": "UgwQSknmkSyQOWDmOOR4AaABAg", "publishedAt": "2022-05-27T08:48:46Z", "author": "Aram Jamkotchian", "text": "set speed to 1.5x\u2b50or you will sleep, although very profoundly and well", "likes": 1}, "replies": [{"id": "UgwQSknmkSyQOWDmOOR4AaABAg.9bX2cl3vupK9bdefLwkBc6", "publishedAt": "2022-05-30T07:44:36Z", "author": "Code Mechanic", "text": "\ud83d\ude42 Thanks for the feedback", "likes": 0}]}, {"topLevelComment": {"id": "UgySrTVbf2dEQwW34CZ4AaABAg", "publishedAt": "2022-05-27T04:51:20Z", "author": "Lucas Rocha", "text": "I don't like SQL Server for example, I need to get a select result and generate script to insert based in values for the query to put in other table or database its impossible without payable tools. In MySQL its easier.", "likes": 1}}, {"topLevelComment": {"id": "UgwvxwLs-BT968qHRfR4AaABAg", "publishedAt": "2022-05-26T21:03:07Z", "author": "Juan Ignacio Briano Quint\u00e1n", "text": "Selent!!!!!!", "likes": 0}}, {"topLevelComment": {"id": "Ugyz4bWPqfbB7f2fQQ94AaABAg", "publishedAt": "2022-05-22T18:31:46Z", "author": "Amol Mestry", "text": "Great course, help me a lot\ud83d\udc4d", "likes": 1}, "replies": [{"id": "Ugyz4bWPqfbB7f2fQQ94AaABAg.9bLDNQi9zAf9bdegzAXUpP", "publishedAt": "2022-05-30T07:44:49Z", "author": "Code Mechanic", "text": "Thanks for the feedback", "likes": 0}]}, {"topLevelComment": {"id": "Ugw3ufkk27sGDUo7iGd4AaABAg", "publishedAt": "2022-05-22T13:41:50Z", "author": "Data Home", "text": "Writing...", "likes": 0}}, {"topLevelComment": {"id": "UgyAR7-mJ6plIck76xp4AaABAg", "publishedAt": "2022-05-19T16:00:01Z", "author": "NK", "text": "Top class quality video", "likes": 1}, "replies": [{"id": "UgyAR7-mJ6plIck76xp4AaABAg.9bDDcK6F8cI9bddy_XCXqG", "publishedAt": "2022-05-30T07:38:29Z", "author": "Code Mechanic", "text": "Thanks for the feedback", "likes": 0}]}, {"topLevelComment": {"id": "UgzNX2pucCTsAQ38XtZ4AaABAg", "publishedAt": "2022-05-19T14:47:03Z", "author": "NK", "text": "At 1:59:11, you have shown an index as lastname,firstname,degreeid. Will the 3rd sql query be able to utilize this index for degreeid?", "likes": 0}}, {"topLevelComment": {"id": "Ugx-uwptfTQEjQ473jZ4AaABAg", "publishedAt": "2022-05-19T04:09:23Z", "author": "Arun Kumar", "text": "Wow great.this is what I was expecting.thank you so much", "likes": 1}, "replies": [{"id": "Ugx-uwptfTQEjQ473jZ4AaABAg.9bBxIR5s7yB9bdeILPJwM_", "publishedAt": "2022-05-30T07:41:19Z", "author": "Code Mechanic", "text": "Thanks for the feedback", "likes": 0}]}, {"topLevelComment": {"id": "Ugwv4eSwM0IekZkHCRh4AaABAg", "publishedAt": "2022-05-18T12:15:41Z", "author": "Bezosphere", "text": "Learning about Databases is so important because almost everything in this world contains a database", "likes": 11}, "replies": [{"id": "Ugwv4eSwM0IekZkHCRh4AaABAg.9bAF9QIMIOS9biy0jidU8H", "publishedAt": "2022-06-01T09:09:53Z", "author": "Code Mechanic", "text": "True", "likes": 0}]}, {"topLevelComment": {"id": "UgxdV2qWjP7UL_DJ1Lh4AaABAg", "publishedAt": "2022-05-18T06:48:47Z", "author": "North-East BLUE", "text": "Thank you so much for this course, exactly what I needed.\ud83e\udd29", "likes": 10}, "replies": [{"id": "UgxdV2qWjP7UL_DJ1Lh4AaABAg.9b9ek1bQ3pV9bAqowNQU-c", "publishedAt": "2022-05-18T17:53:33Z", "author": "Code Mechanic", "text": "Thanks for the feedback", "likes": 1}]}, {"topLevelComment": {"id": "Ugw5m4hU80FqtQtvAmd4AaABAg", "publishedAt": "2022-05-18T06:27:58Z", "author": "Alek Kerm", "text": "Great course, exactly what I needed!", "likes": 2}, "replies": [{"id": "Ugw5m4hU80FqtQtvAmd4AaABAg.9b9cM_MCigs9bAqtf2ySIQ", "publishedAt": "2022-05-18T17:54:11Z", "author": "Code Mechanic", "text": "Thanks for the feedback", "likes": 0}]}, {"topLevelComment": {"id": "UgxZJezGFQvgIJV9hLN4AaABAg", "publishedAt": "2022-05-18T05:39:01Z", "author": "Dhiraj Bhavsar", "text": "We have only one like button \ud83d\ude12 Period", "likes": 0}, "replies": [{"id": "UgxZJezGFQvgIJV9hLN4AaABAg.9b9Xl6eJuE49bArZ43LJBY", "publishedAt": "2022-05-18T17:59:59Z", "author": "Code Mechanic", "text": "Thanks for the feedback", "likes": 0}]}, {"topLevelComment": {"id": "Ugwl2I82Up1Ls0UNLYd4AaABAg", "publishedAt": "2022-05-18T04:41:19Z", "author": "Noddy Choi", "text": "This tutorial is absolutely great and helpful !!!!!.\nHope to see another vid about MySQL and Postgre !!", "likes": 6}, "replies": [{"id": "Ugwl2I82Up1Ls0UNLYd4AaABAg.9b9R9Ua4PX39bAqse2qL5L", "publishedAt": "2022-05-18T17:54:03Z", "author": "Code Mechanic", "text": "Thanks for the feedback", "likes": 0}]}, {"topLevelComment": {"id": "Ugyqm7fbXuJeSHh79HJ4AaABAg", "publishedAt": "2022-05-18T01:01:06Z", "author": "Law B", "text": "Great Course. Thank you so much.", "likes": 3}, "replies": [{"id": "Ugyqm7fbXuJeSHh79HJ4AaABAg.9b91xWaqrXy9bdejHVM1Jj", "publishedAt": "2022-05-30T07:45:08Z", "author": "Code Mechanic", "text": "Thanks for the feedback", "likes": 0}, {"id": "Ugyqm7fbXuJeSHh79HJ4AaABAg.9b91xWaqrXy9bAquzWJyf2", "publishedAt": "2022-05-18T17:54:22Z", "author": "Code Mechanic", "text": "Thanks for the feedback", "likes": 0}]}, {"topLevelComment": {"id": "Ugw2EiNJOS4b58KVWMJ4AaABAg", "publishedAt": "2022-05-18T00:59:20Z", "author": "Rita Sing", "text": "I have idea to make mobile application\n\nWould you like to invest and become a billionaire", "likes": 0}}, {"topLevelComment": {"id": "UgxFNfAPrj9VKb9KdGh4AaABAg", "publishedAt": "2022-05-17T22:30:22Z", "author": "Matthew Lavancher", "text": "A+++++", "likes": 0}, "replies": [{"id": "UgxFNfAPrj9VKb9KdGh4AaABAg.9b8lhXSxRZp9bArStJOc5r", "publishedAt": "2022-05-18T17:59:08Z", "author": "Code Mechanic", "text": "Thanks for the feedback", "likes": 0}]}, {"topLevelComment": {"id": "Ugwz0Z3hOY8mexaR0sh4AaABAg", "publishedAt": "2022-05-17T21:57:06Z", "author": "SuspiciousDev", "text": "The back bone in either backend and front-end.", "likes": 1}}, {"topLevelComment": {"id": "UgxRoz2I7KpHrMKZmJ94AaABAg", "publishedAt": "2022-05-17T20:15:16Z", "author": "Konstantin Hater", "text": "That Indian speaking make me smile)))", "likes": 1}, "replies": [{"id": "UgxRoz2I7KpHrMKZmJ94AaABAg.9b8XF3ZS9DE9b9am3jAy6t", "publishedAt": "2022-05-18T06:14:06Z", "author": "Darkhorse", "text": "The Indian makes my ears cry.", "likes": 1}]}, {"topLevelComment": {"id": "UgzFCDLjlDvb3-0g4NZ4AaABAg", "publishedAt": "2022-05-17T19:38:07Z", "author": "sujaykhandekar", "text": "u r channel deserves 500 million subs", "likes": 2}}, {"topLevelComment": {"id": "Ugzl8YMqZhS9mu1Mv-Z4AaABAg", "publishedAt": "2022-05-17T18:36:15Z", "author": "Mohammed Abdul Sattar", "text": "Hi sir,  the tools which u are used in this video we can also use in oracle sql developer or not???", "likes": 0}, "replies": [{"id": "Ugzl8YMqZhS9mu1Mv-Z4AaABAg.9b8LurPd0uo9bArENTeOEl", "publishedAt": "2022-05-18T17:57:09Z", "author": "Code Mechanic", "text": "Sorry, but this is only for Microsoft SQL Server. it will not be used for Oracle Database", "likes": 0}]}, {"topLevelComment": {"id": "UgzWDHFdRQQvZz-CRRZ4AaABAg", "publishedAt": "2022-05-17T17:54:17Z", "author": "kory", "text": "I coincidentally just started my database course yesterday", "likes": 4}}, {"topLevelComment": {"id": "UgxanEcwNYfy7PV4hNh4AaABAg", "publishedAt": "2022-05-17T16:51:04Z", "author": "kwizera frank", "text": "This was what i was looking for!", "likes": 3}}, {"topLevelComment": {"id": "UgwClMc2OD1qGdNMWft4AaABAg", "publishedAt": "2022-05-17T16:43:40Z", "author": "Mayur Manjal", "text": "Request you to please make a Video on SOC or SIEM \ud83d\ude4f please it will help lot of people like me who can't afford Expensive courses #freeeducationforall", "likes": 0}}, {"topLevelComment": {"id": "UgxyFRhjgSTO5YGyP094AaABAg", "publishedAt": "2022-05-17T16:09:54Z", "author": "Princess Crawforddd", "text": "Your mother", "likes": 2}}, {"topLevelComment": {"id": "UgyUvnh-M-LeLk_WxZN4AaABAg", "publishedAt": "2022-05-17T15:34:19Z", "author": "__________________________________________________", "text": "Where are the links ?", "likes": 0}}, {"topLevelComment": {"id": "Ugy83ujUpnn0cGaCG8d4AaABAg", "publishedAt": "2022-05-17T15:13:16Z", "author": "Michel Chaghoury", "text": "Great tutorial we need more SQL Server tutorials, please in the future make a SQL Server DBA, SSIS, SSRS tuts thank you", "likes": 34}, "replies": [{"id": "Ugy83ujUpnn0cGaCG8d4AaABAg.9b7zg7KZp769bBeOwBIn92", "publishedAt": "2022-05-19T01:24:14Z", "author": "Lillyoko", "text": "\u05e4\u05d9\u05d9\u05d9\u05d1\u05d7\u05d7\u05d9", "likes": 0}, {"id": "Ugy83ujUpnn0cGaCG8d4AaABAg.9b7zg7KZp769bBeOPYaxCD", "publishedAt": "2022-05-19T01:24:10Z", "author": "Lillyoko", "text": "\u05d4\u05d9\u05d9\u05d1\u05d1\u05d7\u05d4\u05d7\u05d7\u05d1\u05e4\u05d9\u05d9\u05d9", "likes": 0}, {"id": "Ugy83ujUpnn0cGaCG8d4AaABAg.9b7zg7KZp769bBeO4a4xdi", "publishedAt": "2022-05-19T01:24:07Z", "author": "Lillyoko", "text": "@Suraj Khot \u05d1", "likes": 0}, {"id": "Ugy83ujUpnn0cGaCG8d4AaABAg.9b7zg7KZp769bBeNnkuKPD", "publishedAt": "2022-05-19T01:24:05Z", "author": "Lillyoko", "text": "@Suraj Khot \u05d1\u05d1\u05d9 \u05d1\u05d1\u05d9\u05e4\u05d1\u05d9\u05d1\u05e4\u05d9", "likes": 0}, {"id": "Ugy83ujUpnn0cGaCG8d4AaABAg.9b7zg7KZp769bBeNSfoA6n", "publishedAt": "2022-05-19T01:24:02Z", "author": "Lillyoko", "text": "@Suraj Khot \u05d7\u05d1\u05e4\u05d9\u05d1\u05e4\u05d9 \u05d9\u05d1 \u05d1\u05d1", "likes": 0}]}, {"topLevelComment": {"id": "Ugxb5uSKlM1axV6Yu2h4AaABAg", "publishedAt": "2022-05-17T15:09:05Z", "author": "Ravi", "text": "Awesome", "likes": 0}, "replies": [{"id": "Ugxb5uSKlM1axV6Yu2h4AaABAg.9b7zCZbUefq9bArHl9ke9H", "publishedAt": "2022-05-18T17:57:37Z", "author": "Code Mechanic", "text": "Thanks for the feedback", "likes": 0}]}, {"topLevelComment": {"id": "UgzKGVJrNhGUa5XO3dN4AaABAg", "publishedAt": "2022-05-17T14:44:22Z", "author": "Shawon Kumar", "text": "Does this work for MySQL database?", "likes": 0}, "replies": [{"id": "UgzKGVJrNhGUa5XO3dN4AaABAg.9b7wNVbkjd99bArYNpRgDP", "publishedAt": "2022-05-18T17:59:53Z", "author": "Code Mechanic", "text": "No Shawon, it only works with Microsoft SQL Server", "likes": 0}, {"id": "UgzKGVJrNhGUa5XO3dN4AaABAg.9b7wNVbkjd99b7xdWEuDdl", "publishedAt": "2022-05-17T14:55:26Z", "author": "Louisianish", "text": "Probably to an extent, but they are different database management systems. I\u2019m sure a lot of this is applicable to other RDBMS like MySQL and PostgreSQL, though.", "likes": 3}]}, {"topLevelComment": {"id": "Ugy-Jd430RB1PWyNPVB4AaABAg", "publishedAt": "2022-05-17T14:43:41Z", "author": "Antonio Garc\u00eda Mar\u00edn", "text": "Thank you so much but sql server no sorry.", "likes": 1}, "replies": [{"id": "Ugy-Jd430RB1PWyNPVB4AaABAg.9b7wIR0GfEX9bCC-RE06xD", "publishedAt": "2022-05-19T06:26:36Z", "author": "Antonio Garc\u00eda Mar\u00edn", "text": "@Rohit It is not a bad product. I use an old version at work and other systems (eg PostgreSQL) are better. IMHO", "likes": 0}, {"id": "Ugy-Jd430RB1PWyNPVB4AaABAg.9b7wIR0GfEX9b9WAnkJeUV", "publishedAt": "2022-05-18T05:25:11Z", "author": "Rohit", "text": "why ? SQL Server is good.", "likes": 0}]}, {"topLevelComment": {"id": "UgyB5kwJHEau3qld7n14AaABAg", "publishedAt": "2022-05-17T14:39:04Z", "author": "Naveen Chandran", "text": "Please post pl/sql course it will help many people", "likes": 0}, "replies": [{"id": "UgyB5kwJHEau3qld7n14AaABAg.9b7vlcp7Qe_9bAraYI6hw7", "publishedAt": "2022-05-18T18:00:19Z", "author": "Code Mechanic", "text": "Noted", "likes": 0}, {"id": "UgyB5kwJHEau3qld7n14AaABAg.9b7vlcp7Qe_9b7wNdnLWOQ", "publishedAt": "2022-05-17T14:44:23Z", "author": "freeCodeCamp.org", "text": "Here are some courses that may help you:\nSQL Course: https://youtu.be/HXV3zeQKqGY\nMySQL Course: https://youtu.be/ER8oKX5myE0\nUniversity Database Systems Course: https://youtu.be/4cWkVbC2bNE", "likes": 4}]}, {"topLevelComment": {"id": "UgzcUC58lkjZoE4XTIJ4AaABAg", "publishedAt": "2022-05-17T14:26:29Z", "author": "RIJU", "text": "KYA BAAT HAI", "likes": 0}, "replies": [{"id": "UgzcUC58lkjZoE4XTIJ4AaABAg.9b7uKWTvEs49bArGoDYKOZ", "publishedAt": "2022-05-18T17:57:29Z", "author": "Code Mechanic", "text": "Thanks for the feedback", "likes": 1}]}, {"topLevelComment": {"id": "UgwWa-GnCF5k3pkCYkh4AaABAg", "publishedAt": "2022-05-17T14:22:06Z", "author": "Aybe", "text": "SSIS please!", "likes": 1}, "replies": [{"id": "UgwWa-GnCF5k3pkCYkh4AaABAg.9b7tpRkH-jf9bAqwdmQbjq", "publishedAt": "2022-05-18T17:54:36Z", "author": "Code Mechanic", "text": "Noted", "likes": 0}]}, {"topLevelComment": {"id": "UgxCsFmzM5VqAtgrF694AaABAg", "publishedAt": "2022-05-17T14:20:13Z", "author": "Universe Code", "text": "I am a self-taught developer \ud83d\ude0d who after years of Js and React, and on my YouTube channel \ud83e\uddd1\ud83c\udffb\u200d\ud83d\udcbb I create projects with React and tailwind or Html and Css\u2026 right now I\u2019m learning Python and as you well know, SQL is part of his world.  This video comes at the right time \ud83d\ude0e", "likes": 15}}, {"topLevelComment": {"id": "Ugx37lQjgB662dwFY-t4AaABAg", "publishedAt": "2022-05-17T14:19:14Z", "author": "Ayomide Ayodele-Soyebo", "text": "You guys are the best!", "likes": 6}, "replies": [{"id": "Ugx37lQjgB662dwFY-t4AaABAg.9b7tVQ3MMRz9bAreyoLisj", "publishedAt": "2022-05-18T18:00:55Z", "author": "Code Mechanic", "text": "Thanks for the feedback", "likes": 1}]}, {"topLevelComment": {"id": "UgxsaMQv54X489avkfp4AaABAg", "publishedAt": "2022-05-17T14:17:03Z", "author": "Vincent Ray Alba", "text": "Can you make solid works video plzzzz.", "likes": 1}, "replies": [{"id": "UgxsaMQv54X489avkfp4AaABAg.9b7tFSzKMgL9b7xlWRftDe", "publishedAt": "2022-05-17T14:56:31Z", "author": "Louisianish", "text": "I\u2019m sure they\u2019re working on it. Solid is a fairly new framework, right?", "likes": 1}]}, {"topLevelComment": {"id": "Ugxqg0BAc-Al0XCO7-p4AaABAg", "publishedAt": "2022-05-17T14:12:44Z", "author": "Mahesh mahi", "text": "Great job from you people.", "likes": 11}, "replies": [{"id": "Ugxqg0BAc-Al0XCO7-p4AaABAg.9b7skkCxsjt9bC0oHlnnFH", "publishedAt": "2022-05-19T04:48:49Z", "author": "Rajan Arora", "text": "@Sid Ch \ud83d\ude4f", "likes": 0}, {"id": "Ugxqg0BAc-Al0XCO7-p4AaABAg.9b7skkCxsjt9bAre5xFwP6", "publishedAt": "2022-05-18T18:00:48Z", "author": "Code Mechanic", "text": "Thanks for the feedback", "likes": 0}]}, {"topLevelComment": {"id": "UgwOleNpJn-KbW_y4ER4AaABAg", "publishedAt": "2022-05-17T14:11:46Z", "author": "Samuel Mbah", "text": "I love you guys \u2764\ufe0f\u2764\ufe0f\u2764\ufe0f", "likes": 1}}, {"topLevelComment": {"id": "UgxhuWnuEGwAj1HgzVd4AaABAg", "publishedAt": "2022-05-17T14:09:55Z", "author": "BlueShardStudio", "text": "Hi freeCodeCamp! I'd like to ask you if you can make tutorial for C++ desktop development. Thanks \ud83d\ude00", "likes": 0}, "replies": [{"id": "UgxhuWnuEGwAj1HgzVd4AaABAg.9b7sR5SLr1A9b7slwev3Zr", "publishedAt": "2022-05-17T14:12:53Z", "author": "Ahmad Faisal", "text": "They already make it, go check it", "likes": 0}]}, {"topLevelComment": {"id": "Ugy5kPquX0okDXuP7YJ4AaABAg", "publishedAt": "2022-05-17T14:08:36Z", "author": "aditya vikram sinha", "text": "Olaaa", "likes": 0}}, {"topLevelComment": {"id": "UgzjnLIKko2m38vmJU94AaABAg", "publishedAt": "2022-05-17T14:08:06Z", "author": "Soumadip Banerjee", "text": "\u2764\ufe0f", "likes": 2}}, {"topLevelComment": {"id": "UgzF9HvZqNAnPR0OYYF4AaABAg", "publishedAt": "2022-05-17T14:08:00Z", "author": "\u0628\u0631\u0646\u0633 \u0627\u0644\u0645\u0644\u062e\u0635\u0627\u062a", "text": "\u064a\u0627\u0631\u0628 \u0627\u062a\u0648\u0633\u0644 \u0625\u064a\u0644\u064a\u0643 \u0628\u062d\u0642 \u0625\u0633\u0645\u0643 \u0627\u0644\u0627\u0639\u0636\u0645 \u0627\u0646 \u062a\u0631\u0632\u0642 \u0635\u0627\u062d\u0628 \u0627\u0644\u064a\u062f \u0627\u0644\u062a\u064a \u0633\u062a\u062f\u0639\u0640\u0640\u0645\u0646\u0640\u0640\u0640\u064a \u0628\u0627 \u0645\u062a\u0627\u0628\u0639\u0629 \u0648\u0631\u0632\u0642 \u0644\u0627\u064a\u0646\u062a\u0647\u064a \u0648\u062a\u0648\u0641\u064a\u0642 \u0644\u0627\u0646\u0647\u0627\u064a\u0647 \ud83d\udc94\ud83d\udc94\ud83d\ude2d.", "likes": 1}}, {"topLevelComment": {"id": "UgzLEG-59zfMyO7vBYF4AaABAg", "publishedAt": "2022-05-17T14:07:45Z", "author": "Orion YT", "text": "2nd", "likes": 0}}, {"topLevelComment": {"id": "UgzPAVs5cx6q9UDnmR94AaABAg", "publishedAt": "2022-05-17T14:07:37Z", "author": "nishiki San", "text": "hay bruh", "likes": 0}, "replies": [{"id": "UgzPAVs5cx6q9UDnmR94AaABAg.9b7sAHS_31d9b8XxbJpZ8a", "publishedAt": "2022-05-17T20:21:29Z", "author": "Journey2success", "text": "Hay bruh", "likes": 0}, {"id": "UgzPAVs5cx6q9UDnmR94AaABAg.9b7sAHS_31d9b7tc9tssdb", "publishedAt": "2022-05-17T14:20:17Z", "author": "ritik sharma", "text": "hay bruh", "likes": 0}, {"id": "UgzPAVs5cx6q9UDnmR94AaABAg.9b7sAHS_31d9b7sJIjQPOt", "publishedAt": "2022-05-17T14:08:51Z", "author": "Journey2success", "text": "Hay bruh", "likes": 0}]}]}